confuk/__init__.py
confuk/display.py
confuk/doc.py
confuk/dump.py
confuk/logging.py
confuk/main.py
confuk/main_decorator.py
confuk/parse.py
confuk-0.14.0.dist-info/METADATA
confuk-0.14.0.dist-info/WHEEL
confuk-0.14.0.dist-info/entry_points.txt
confuk-0.14.0.dist-info/licenses/LICENSE
confuk-0.14.0.dist-info/RECORD
