Metadata-Version: 2.4
Name: confuk
Version: 0.14.0
Summary: Yet another configuration loading package for Python projects
License: MIT
License-File: LICENSE
Author: Krzysztof J. Czarnecki
Author-email: kjczarne@gmail.com
Requires-Python: >=3.10,<4.0
Classifier: License :: OSI Approved :: MIT License
Classifier: Programming Language :: Python :: 3
Classifier: Programming Language :: Python :: 3.10
Classifier: Programming Language :: Python :: 3.11
Classifier: Programming Language :: Python :: 3.12
Classifier: Programming Language :: Python :: 3.13
Classifier: Programming Language :: Python :: 3.14
Requires-Dist: click (>=8.1.8,<9.0.0)
Requires-Dist: easydict (>=1.11,<2.0)
Requires-Dist: jsonpickle (>=4.0.2,<5.0.0)
Requires-Dist: markdown (>=3.8,<4.0)
Requires-Dist: omegaconf (>=2.3.0,<3.0.0)
Requires-Dist: pydantic (>=2.5.3,<3.0.0)
Requires-Dist: rich (>=13.8.1,<14.0.0)
Requires-Dist: ruamel-yaml (>=0.18.6,<0.19.0)
Requires-Dist: toml (>=0.10.2,<0.11.0)
